sigilo/__init__.py
sigilo/ciphers/__init__.py
sigilo/ciphers/fernet.py
sigilo/ciphers/plain.py
sigilo/stores/__init__.py
sigilo/stores/memcache.py
sigilo/stores/memory.py
sigilo/stores/redis.py
sigilo-0.2.0.dist-info/METADATA
sigilo-0.2.0.dist-info/WHEEL
sigilo-0.2.0.dist-info/licenses/LICENSE
sigilo-0.2.0.dist-info/RECORD
