Metadata-Version: 2.1
Name: sigilo
Version: 0.2.0
Project-URL: Source, https://github.com/ecarrara/sigilo
Project-URL: Issues, https://github.com/ecarrara/sigilo/issues
Author-email: Erle Carrara <carrara.erle@gmail.com>
License-File: LICENSE
Classifier: License :: OSI Approved :: MIT License
Classifier: Operating System :: OS Independent
Classifier: Programming Language :: Python :: 3
Requires-Python: >=3.8
Provides-Extra: cryptography
Requires-Dist: cryptography; extra == 'cryptography'
Provides-Extra: pymemcache
Requires-Dist: pymemcache; extra == 'pymemcache'
Provides-Extra: redis
Requires-Dist: redis; extra == 'redis'
